COPYING
MANIFEST.in
README
health_reporting_report.xml
health_reporting_view.xml
setup.py
./__init__.py
./health_reporting_report.xml
./health_reporting_view.xml
./tryton.cfg
./doc/index.rst
./locale/ar.po
./locale/de.po
./locale/el.po
./locale/es.po
./locale/fr.po
./locale/it_IT.po
./locale/ja_JP.po
./locale/lo.po
./locale/pt_BR.po
./locale/zh_CN.po
./report/__init__.py
./report/summary_report.odt
./report/summary_report.py
./tests/__init__.py
./tests/test_health_reporting.py
./view/evaluations_doctor_graph.xml
./view/evaluations_doctor_tree.xml
./view/evaluations_open_start_form.xml
./view/evaluations_sector_graph.xml
./view/evaluations_sector_tree.xml
./view/evaluations_specialty_graph.xml
./view/evaluations_specialty_tree.xml
./view/summary_report_open_start_form.xml
./view/top_diseases_graph.xml
./view/top_diseases_open_start_form.xml
./view/top_diseases_tree.xml
./wizard/__init__.py
./wizard/evaluations.xml
./wizard/summary_report_wizard.xml
./wizard/top_diseases.xml
./wizard/wizard_evaluations.py
./wizard/wizard_summary_report.py
./wizard/wizard_top_diseases.py
locale/ar.po
locale/de.po
locale/el.po
locale/es.po
locale/fr.po
locale/it_IT.po
locale/ja_JP.po
locale/lo.po
locale/pt_BR.po
locale/zh_CN.po
trytond_health_reporting.egg-info/PKG-INFO
trytond_health_reporting.egg-info/SOURCES.txt
trytond_health_reporting.egg-info/dependency_links.txt
trytond_health_reporting.egg-info/entry_points.txt
trytond_health_reporting.egg-info/not-zip-safe
trytond_health_reporting.egg-info/requires.txt
trytond_health_reporting.egg-info/top_level.txt
view/evaluations_doctor_graph.xml
view/evaluations_doctor_tree.xml
view/evaluations_open_start_form.xml
view/evaluations_sector_graph.xml
view/evaluations_sector_tree.xml
view/evaluations_specialty_graph.xml
view/evaluations_specialty_tree.xml
view/summary_report_open_start_form.xml
view/top_diseases_graph.xml
view/top_diseases_open_start_form.xml
view/top_diseases_tree.xml
wizard/evaluations.xml
wizard/summary_report_wizard.xml
wizard/top_diseases.xml